setup.cfg
setup.py
mixpanel3/__init__.py
mixpanel3.egg-info/PKG-INFO
mixpanel3.egg-info/SOURCES.txt
mixpanel3.egg-info/dependency_links.txt
mixpanel3.egg-info/not-zip-safe
mixpanel3.egg-info/requires.txt
mixpanel3.egg-info/top_level.txt