Metadata-Version: 1.0
Name: mixpanel3
Version: 0.1
Summary: Utility library to work with mixpanel API
Home-page: https://github.com/ittus/python-mixpanel3
Author: ittus
Author-email: vuminhthang.cm@gmail.com
License: MIT
Keywords: mixpanel,tracking,data,analytic
Platform: UNKNOWN
